nofications/__init__.py
nofications-1.0.4.dist-info/licenses/LICENSE
nofications-1.0.4.dist-info/METADATA
nofications-1.0.4.dist-info/WHEEL
nofications-1.0.4.dist-info/entry_points.txt
nofications-1.0.4.dist-info/top_level.txt
nofications-1.0.4.dist-info/RECORD
