Metadata-Version: 2.4
Name: Nofications
Version: 1.0.4
Summary: Show notification pop-ups
Author-email: xBlake_2012x <Blake_Brent@outlook.com>
License: MIT License
Project-URL: Homepage, https://github.com/xBlake-2012x/Nofication-pythonlibrary
Project-URL: Repository, https://github.com/xBlake-2012x/Nofication-pythonlibrary
Classifier: License :: OSI Approved :: MIT License
Classifier: Programming Language :: Python :: 3
Requires-Python: >=3.6
License-File: LICENSE
Dynamic: license-file
